{
	"credit": "Made with Blockbench, a free, modern block model editor by JannisX11",
	"textures": {
		"0": "scollectibles:blocks/ender_dragon_figure",
		"particle": "scollectibles:blocks/ender_dragon_figure"
	},
	"elements": [
		{
			"from": [6.5, 30.75, -10.175],
			"to": [7, 32, -7.925],
			"rotation": {"angle": 0, "axis": "y", "origin": [8.25, 31.375, -9.175]},
			"faces": {
				"north": {"uv": [10.75, 2.75, 11, 3.25], "texture": "#0"},
				"east": {"uv": [10, 2.75, 10.75, 3.25], "texture": "#0"},
				"south": {"uv": [11, 2.75, 11.25, 3.25], "texture": "#0"},
				"west": {"uv": [11.25, 2.75, 12, 3.25], "texture": "#0"},
				"up": {"uv": [10.75, 2, 11, 2.75], "texture": "#0"},
				"down": {"uv": [11, 2, 11.25, 2.75], "texture": "#0"}
			}
		},
		{
			"from": [5.25, 24.75, -12.175],
			"to": [11.25, 30.75, -6.175],
			"rotation": {"angle": 0, "axis": "y", "origin": [8.25, 27.75, -9.175]},
			"faces": {
				"north": {"uv": [1.5, 1.5, 3, 3], "texture": "#0"},
				"east": {"uv": [3, 1.5, 4.5, 3], "texture": "#0"},
				"south": {"uv": [3, 1.5, 4.5, 3], "texture": "#0"},
				"west": {"uv": [3, 1.5, 4.5, 3], "texture": "#0"},
				"up": {"uv": [1.5, 0, 3, 1.5], "texture": "#0"},
				"down": {"uv": [3, 1.5, 4.5, 3], "texture": "#0"}
			}
		},
		{
			"from": [6.25, 25.25, -16],
			"to": [10.25, 26.25, -12],
			"rotation": {"angle": 0, "axis": "y", "origin": [9.25, 25.75, -11.75]},
			"faces": {
				"north": {"uv": [10, 1.5, 11.5, 1.75], "texture": "#0"},
				"east": {"uv": [10, 1.5, 11.5, 1.75], "texture": "#0"},
				"south": {"uv": [10, 1.5, 11.5, 1.75], "texture": "#0"},
				"west": {"uv": [10, 1.5, 11.5, 1.75], "texture": "#0"},
				"up": {"uv": [11.5, 0, 12.5, 1], "texture": "#0", "rotation": 180},
				"down": {"uv": [12.5, 0, 13.5, 1], "texture": "#0", "rotation": 180}
			}
		},
		{
			"from": [6.25, 26.75, -16],
			"to": [10.25, 27.75, -12],
			"rotation": {"angle": 0, "axis": "y", "origin": [9.25, 27.25, -11.75]},
			"faces": {
				"north": {"uv": [10, 1.5, 11.5, 1.75], "texture": "#0"},
				"east": {"uv": [10, 1.5, 11.5, 1.75], "texture": "#0"},
				"south": {"uv": [10, 1.5, 11.5, 1.75], "texture": "#0"},
				"west": {"uv": [10, 1.5, 11.5, 1.75], "texture": "#0"},
				"up": {"uv": [12.5, 0, 13.5, 1], "texture": "#0"},
				"down": {"uv": [11.5, 0, 12.5, 1], "texture": "#0"}
			}
		},
		{
			"from": [9, 27.75, -16],
			"to": [9.5, 28.5, -15],
			"rotation": {"angle": 0, "axis": "y", "origin": [9.25, 28.125, -11.75]},
			"faces": {
				"north": {"uv": [10.25, 0, 10.75, 0.5], "texture": "#0"},
				"east": {"uv": [10.25, 0, 10.75, 0.5], "texture": "#0"},
				"south": {"uv": [10.25, 0, 10.75, 0.5], "texture": "#0"},
				"west": {"uv": [10.25, 0, 10.75, 0.5], "texture": "#0"},
				"up": {"uv": [10.25, 0, 10.75, 0.5], "texture": "#0"},
				"down": {"uv": [10.25, 0, 10.75, 0.5], "texture": "#0"}
			}
		},
		{
			"from": [7, 27.75, -16],
			"to": [7.5, 28.5, -15],
			"rotation": {"angle": 0, "axis": "y", "origin": [9.25, 28.125, -11.75]},
			"faces": {
				"north": {"uv": [10.25, 0, 10.75, 0.5], "texture": "#0"},
				"east": {"uv": [10.25, 0, 10.75, 0.5], "texture": "#0"},
				"south": {"uv": [10.25, 0, 10.75, 0.5], "texture": "#0"},
				"west": {"uv": [10.25, 0, 10.75, 0.5], "texture": "#0"},
				"up": {"uv": [10.25, 0, 10.75, 0.5], "texture": "#0"},
				"down": {"uv": [10.25, 0, 10.75, 0.5], "texture": "#0"}
			}
		},
		{
			"from": [9.5, 30.75, -10.175],
			"to": [10, 32, -7.925],
			"rotation": {"angle": 0, "axis": "y", "origin": [8.25, 31.375, -9.175]},
			"faces": {
				"north": {"uv": [10.75, 2.75, 11, 3.25], "texture": "#0"},
				"east": {"uv": [10, 2.75, 10.75, 3.25], "texture": "#0"},
				"south": {"uv": [11, 2.75, 11.25, 3.25], "texture": "#0"},
				"west": {"uv": [11.25, 2.75, 12, 3.25], "texture": "#0"},
				"up": {"uv": [10.75, 2, 11, 2.75], "texture": "#0"},
				"down": {"uv": [11, 2, 11.25, 2.75], "texture": "#0"}
			}
		},
		{
			"from": [4, 10, 2.5],
			"to": [12, 18, 26.5],
			"rotation": {"angle": 22.5, "axis": "x", "origin": [8, 14, 14.5]},
			"faces": {
				"north": {"uv": [6, 6, 8, 8], "texture": "#0"},
				"east": {"uv": [10, 6, 16, 8], "texture": "#0"},
				"south": {"uv": [8, 6, 10, 8], "texture": "#0"},
				"west": {"uv": [0, 6, 6, 8], "texture": "#0"},
				"up": {"uv": [6, 0, 8, 6], "texture": "#0"},
				"down": {"uv": [8, 0, 10, 6], "texture": "#0"}
			}
		},
		{
			"from": [7.5, 18, 12.25],
			"to": [8.5, 21, 17.25],
			"rotation": {"angle": 22.5, "axis": "x", "origin": [8, 14, 14.5]},
			"faces": {
				"north": {"uv": [12.25, 3.5, 12.75, 4.25], "texture": "#0"},
				"east": {"uv": [10.75, 3.5, 12.25, 4.25], "texture": "#0"},
				"south": {"uv": [12.75, 3.5, 13.25, 4.25], "texture": "#0"},
				"west": {"uv": [13.25, 3.5, 14.75, 4.25], "texture": "#0"},
				"up": {"uv": [12.25, 2, 12.75, 3.5], "texture": "#0", "rotation": 180},
				"down": {"uv": [12.75, 2, 13.25, 3.5], "texture": "#0"}
			}
		},
		{
			"from": [7.5, 18, 5],
			"to": [8.5, 21, 10],
			"rotation": {"angle": 22.5, "axis": "x", "origin": [8, 14, 14.5]},
			"faces": {
				"north": {"uv": [12.25, 3.5, 12.75, 4.25], "texture": "#0"},
				"east": {"uv": [10.75, 3.5, 12.25, 4.25], "texture": "#0"},
				"south": {"uv": [12.75, 3.5, 13.25, 4.25], "texture": "#0"},
				"west": {"uv": [13.25, 3.5, 14.75, 4.25], "texture": "#0"},
				"up": {"uv": [12.25, 2, 12.75, 3.5], "texture": "#0", "rotation": 180},
				"down": {"uv": [12.75, 2, 13.25, 3.5], "texture": "#0"}
			}
		},
		{
			"from": [7.5, 18, 19.25],
			"to": [8.5, 21, 24.25],
			"rotation": {"angle": 22.5, "axis": "x", "origin": [8, 14, 14.5]},
			"faces": {
				"north": {"uv": [12.25, 3.5, 12.75, 4.25], "texture": "#0"},
				"east": {"uv": [10.75, 3.5, 12.25, 4.25], "texture": "#0"},
				"south": {"uv": [12.75, 3.5, 13.25, 4.25], "texture": "#0"},
				"west": {"uv": [13.25, 3.5, 14.75, 4.25], "texture": "#0"},
				"up": {"uv": [12.25, 2, 12.75, 3.5], "texture": "#0", "rotation": 180},
				"down": {"uv": [12.75, 2, 13.25, 3.5], "texture": "#0"}
			}
		},
		{
			"from": [-2.5, 0, 3.075],
			"to": [1.5, 4, 7.075],
			"rotation": {"angle": -45, "axis": "y", "origin": [-0.5, 2, 5.075]},
			"faces": {
				"north": {"uv": [10.75, 4.75, 11.75, 5.75], "texture": "#0"},
				"east": {"uv": [10.75, 4.75, 11.75, 5.75], "texture": "#0"},
				"south": {"uv": [10.75, 4.75, 11.75, 5.75], "texture": "#0"},
				"west": {"uv": [10.75, 4.75, 11.75, 5.75], "texture": "#0"},
				"up": {"uv": [10.75, 4.75, 11.75, 5.75], "texture": "#0"},
				"down": {"uv": [10.75, 4.75, 11.75, 5.75], "texture": "#0"}
			}
		},
		{
			"from": [-0.75, 4, 3.825],
			"to": [-0.25, 5.25, 6.075],
			"rotation": {"angle": -45, "axis": "y", "origin": [-0.5, 4.625, 4.95]},
			"faces": {
				"north": {"uv": [10.75, 2.75, 11, 3.25], "texture": "#0"},
				"east": {"uv": [10, 2.75, 10.75, 3.25], "texture": "#0"},
				"south": {"uv": [11, 2.75, 11.25, 3.25], "texture": "#0"},
				"west": {"uv": [11.25, 2.75, 12, 3.25], "texture": "#0"},
				"up": {"uv": [10.75, 2, 11, 2.75], "texture": "#0"},
				"down": {"uv": [11, 2, 11.25, 2.75], "texture": "#0"}
			}
		},
		{
			"from": [-4.25, 0, 6.075],
			"to": [-0.25, 4, 10.075],
			"rotation": {"angle": -22.5, "axis": "y", "origin": [-2.25, 2, 8.075]},
			"faces": {
				"north": {"uv": [10.75, 4.75, 11.75, 5.75], "texture": "#0"},
				"east": {"uv": [10.75, 4.75, 11.75, 5.75], "texture": "#0"},
				"south": {"uv": [10.75, 4.75, 11.75, 5.75], "texture": "#0"},
				"west": {"uv": [10.75, 4.75, 11.75, 5.75], "texture": "#0"},
				"up": {"uv": [10.75, 4.75, 11.75, 5.75], "texture": "#0"},
				"down": {"uv": [10.75, 4.75, 11.75, 5.75], "texture": "#0"}
			}
		},
		{
			"from": [-2.5, 4, 6.825],
			"to": [-2, 5.25, 9.075],
			"rotation": {"angle": -22.5, "axis": "y", "origin": [-2.25, 4.625, 7.95]},
			"faces": {
				"north": {"uv": [10.75, 2.75, 11, 3.25], "texture": "#0"},
				"east": {"uv": [10, 2.75, 10.75, 3.25], "texture": "#0"},
				"south": {"uv": [11, 2.75, 11.25, 3.25], "texture": "#0"},
				"west": {"uv": [11.25, 2.75, 12, 3.25], "texture": "#0"},
				"up": {"uv": [10.75, 2, 11, 2.75], "texture": "#0"},
				"down": {"uv": [11, 2, 11.25, 2.75], "texture": "#0"}
			}
		},
		{
			"from": [-4.5, 0, 13.575],
			"to": [-0.5, 4, 17.575],
			"rotation": {"angle": 0, "axis": "y", "origin": [-2.5, 2, 15.575]},
			"faces": {
				"north": {"uv": [10.75, 4.75, 11.75, 5.75], "texture": "#0"},
				"east": {"uv": [10.75, 4.75, 11.75, 5.75], "texture": "#0"},
				"south": {"uv": [10.75, 4.75, 11.75, 5.75], "texture": "#0"},
				"west": {"uv": [10.75, 4.75, 11.75, 5.75], "texture": "#0"},
				"up": {"uv": [10.75, 4.75, 11.75, 5.75], "texture": "#0"},
				"down": {"uv": [10.75, 4.75, 11.75, 5.75], "texture": "#0"}
			}
		},
		{
			"from": [-2.75, 4, 14.325],
			"to": [-2.25, 5.25, 16.575],
			"rotation": {"angle": 0, "axis": "y", "origin": [-2.5, 4.625, 15.45]},
			"faces": {
				"north": {"uv": [10.75, 2.75, 11, 3.25], "texture": "#0"},
				"east": {"uv": [10, 2.75, 10.75, 3.25], "texture": "#0"},
				"south": {"uv": [11, 2.75, 11.25, 3.25], "texture": "#0"},
				"west": {"uv": [11.25, 2.75, 12, 3.25], "texture": "#0"},
				"up": {"uv": [10.75, 2, 11, 2.75], "texture": "#0"},
				"down": {"uv": [11, 2, 11.25, 2.75], "texture": "#0"}
			}
		},
		{
			"from": [-3.5, 0, 20.825],
			"to": [0.5, 4, 24.825],
			"rotation": {"angle": 22.5, "axis": "y", "origin": [-1.5, 2, 22.825]},
			"faces": {
				"north": {"uv": [10.75, 4.75, 11.75, 5.75], "texture": "#0"},
				"east": {"uv": [10.75, 4.75, 11.75, 5.75], "texture": "#0"},
				"south": {"uv": [10.75, 4.75, 11.75, 5.75], "texture": "#0"},
				"west": {"uv": [10.75, 4.75, 11.75, 5.75], "texture": "#0"},
				"up": {"uv": [10.75, 4.75, 11.75, 5.75], "texture": "#0"},
				"down": {"uv": [10.75, 4.75, 11.75, 5.75], "texture": "#0"}
			}
		},
		{
			"from": [-1.75, 4, 21.575],
			"to": [-1.25, 5.25, 23.825],
			"rotation": {"angle": 22.5, "axis": "y", "origin": [-1.5, 4.625, 22.7]},
			"faces": {
				"north": {"uv": [10.75, 2.75, 11, 3.25], "texture": "#0"},
				"east": {"uv": [10, 2.75, 10.75, 3.25], "texture": "#0"},
				"south": {"uv": [11, 2.75, 11.25, 3.25], "texture": "#0"},
				"west": {"uv": [11.25, 2.75, 12, 3.25], "texture": "#0"},
				"up": {"uv": [10.75, 2, 11, 2.75], "texture": "#0"},
				"down": {"uv": [11, 2, 11.25, 2.75], "texture": "#0"}
			}
		},
		{
			"from": [-1.5, 0, 23.75],
			"to": [2.5, 4, 27.75],
			"rotation": {"angle": 45, "axis": "y", "origin": [0.5, 2, 25.75]},
			"faces": {
				"north": {"uv": [10.75, 4.75, 11.75, 5.75], "texture": "#0"},
				"east": {"uv": [10.75, 4.75, 11.75, 5.75], "texture": "#0"},
				"south": {"uv": [10.75, 4.75, 11.75, 5.75], "texture": "#0"},
				"west": {"uv": [10.75, 4.75, 11.75, 5.75], "texture": "#0"},
				"up": {"uv": [10.75, 4.75, 11.75, 5.75], "texture": "#0"},
				"down": {"uv": [10.75, 4.75, 11.75, 5.75], "texture": "#0"}
			}
		},
		{
			"from": [0.25, 4, 25.075],
			"to": [0.75, 5.25, 27.325],
			"rotation": {"angle": 45, "axis": "y", "origin": [0.5, 4.625, 26.2]},
			"faces": {
				"north": {"uv": [10.75, 2.75, 11, 3.25], "texture": "#0"},
				"east": {"uv": [10, 2.75, 10.75, 3.25], "texture": "#0"},
				"south": {"uv": [11, 2.75, 11.25, 3.25], "texture": "#0"},
				"west": {"uv": [11.25, 2.75, 12, 3.25], "texture": "#0"},
				"up": {"uv": [10.75, 2, 11, 2.75], "texture": "#0"},
				"down": {"uv": [11, 2, 11.25, 2.75], "texture": "#0"}
			}
		},
		{
			"from": [4.75, 1.75, 25.1],
			"to": [8.75, 5.75, 29.1],
			"rotation": {"angle": 45, "axis": "z", "origin": [6.75, 3.75, 27.1]},
			"faces": {
				"north": {"uv": [10.75, 4.75, 11.75, 5.75], "texture": "#0"},
				"east": {"uv": [10.75, 4.75, 11.75, 5.75], "texture": "#0"},
				"south": {"uv": [10.75, 4.75, 11.75, 5.75], "texture": "#0"},
				"west": {"uv": [10.75, 4.75, 11.75, 5.75], "texture": "#0"},
				"up": {"uv": [10.75, 4.75, 11.75, 5.75], "texture": "#0"},
				"down": {"uv": [10.75, 4.75, 11.75, 5.75], "texture": "#0"}
			}
		},
		{
			"from": [5.5, 3.5, 29.025],
			"to": [7.75, 4, 30.275],
			"rotation": {"angle": 45, "axis": "z", "origin": [6.625, 3.75, 29.65]},
			"faces": {
				"north": {"uv": [10, 2.75, 10.75, 3.25], "texture": "#0", "rotation": 180},
				"east": {"uv": [10, 2.75, 10.75, 3.25], "texture": "#0", "rotation": 180},
				"south": {"uv": [10, 2.75, 10.75, 3.25], "texture": "#0", "rotation": 180},
				"west": {"uv": [10, 2.75, 10.75, 3.25], "texture": "#0", "rotation": 180},
				"up": {"uv": [10.75, 2.75, 10, 3.25], "texture": "#0", "rotation": 180},
				"down": {"uv": [10, 2.75, 10.75, 3.25], "texture": "#0"}
			}
		},
		{
			"from": [6, 4.5, 25.075],
			"to": [10, 8.5, 29.075],
			"faces": {
				"north": {"uv": [10.75, 4.75, 11.75, 5.75], "texture": "#0"},
				"east": {"uv": [10.75, 4.75, 11.75, 5.75], "texture": "#0"},
				"south": {"uv": [10.75, 4.75, 11.75, 5.75], "texture": "#0"},
				"west": {"uv": [10.75, 4.75, 11.75, 5.75], "texture": "#0"},
				"up": {"uv": [10.75, 4.75, 11.75, 5.75], "texture": "#0"},
				"down": {"uv": [10.75, 4.75, 11.75, 5.75], "texture": "#0"}
			}
		},
		{
			"from": [7.75, 5.25, 29.075],
			"to": [8.25, 7.5, 30.325],
			"faces": {
				"north": {"uv": [10.75, 2.75, 11, 3.25], "texture": "#0"},
				"east": {"uv": [10, 2.75, 10.75, 3.25], "texture": "#0", "rotation": 270},
				"south": {"uv": [11, 2.75, 11.25, 3.25], "texture": "#0"},
				"west": {"uv": [11.25, 2.75, 12, 3.25], "texture": "#0", "rotation": 90},
				"up": {"uv": [10.75, 2, 11, 2.75], "texture": "#0"},
				"down": {"uv": [11, 2, 11.25, 2.75], "texture": "#0"}
			}
		},
		{
			"from": [30.65, 6.95, 5.25],
			"to": [30.65, 27.95, 26.25],
			"rotation": {"angle": 22.5, "axis": "z", "origin": [30.65, 28.2, 15.75]},
			"faces": {
				"north": {"uv": [0, 8, 5.25, 13.25], "texture": "#0", "rotation": 270},
				"east": {"uv": [5.25, 8, 10.5, 13.25], "texture": "#0", "rotation": 270},
				"south": {"uv": [0, 8, 5.25, 13.25], "texture": "#0", "rotation": 90},
				"west": {"uv": [5.25, 13.25, 10.5, 8], "texture": "#0", "rotation": 270},
				"up": {"uv": [0, 8, 5.25, 13.25], "texture": "#0", "rotation": 90},
				"down": {"uv": [0, 8, 5.25, 13.25], "texture": "#0", "rotation": 90}
			}
		},
		{
			"from": [10, 27.675, 5.25],
			"to": [31, 27.675, 26.25],
			"rotation": {"angle": 22.5, "axis": "z", "origin": [30.5, 27.675, 15.75]},
			"faces": {
				"north": {"uv": [0, 8, 5.25, 13.25], "texture": "#0"},
				"east": {"uv": [0, 8, 5.25, 13.25], "texture": "#0"},
				"south": {"uv": [0, 8, 5.25, 13.25], "texture": "#0"},
				"west": {"uv": [0, 8, 5.25, 13.25], "texture": "#0"},
				"up": {"uv": [0, 8, 5.25, 13.25], "texture": "#0", "rotation": 180},
				"down": {"uv": [0, 13.25, 5.25, 8], "texture": "#0", "rotation": 180}
			}
		},
		{
			"from": [30.15, 6.95, 4.75],
			"to": [31.15, 11.95, 5.75],
			"rotation": {"angle": 22.5, "axis": "z", "origin": [30.65, 28.2, 15.75]},
			"faces": {
				"north": {"uv": [11, 8.5, 12.75, 8.75], "texture": "#0", "rotation": 270},
				"east": {"uv": [11, 8.5, 12.75, 8.75], "texture": "#0", "rotation": 90},
				"south": {"uv": [11, 8.5, 12.75, 8.75], "texture": "#0", "rotation": 90},
				"west": {"uv": [11, 8.5, 12.75, 8.75], "texture": "#0", "rotation": 90},
				"up": {"uv": [11, 8.5, 12.75, 8.75], "texture": "#0", "rotation": 90},
				"down": {"uv": [11, 8.5, 12.75, 8.75], "texture": "#0", "rotation": 90}
			}
		},
		{
			"from": [10, 26.675, 4.25],
			"to": [14, 28.675, 6.25],
			"rotation": {"angle": 22.5, "axis": "z", "origin": [30.5, 27.675, 5.25]},
			"faces": {
				"north": {"uv": [14.5, 8, 16, 8.75], "texture": "#0"},
				"east": {"uv": [14.5, 8, 16, 8.75], "texture": "#0"},
				"south": {"uv": [14.5, 8, 16, 8.75], "texture": "#0"},
				"west": {"uv": [15.25, 8, 16, 8.75], "texture": "#0"},
				"up": {"uv": [14.5, 8, 16, 8.75], "texture": "#0"},
				"down": {"uv": [14.5, 8, 16, 8.75], "texture": "#0"}
			}
		},
		{
			"from": [30.15, 10.95, 4.75],
			"to": [31.15, 27.95, 5.75],
			"rotation": {"angle": 22.5, "axis": "z", "origin": [30.65, 28.2, 15.75]},
			"faces": {
				"north": {"uv": [10.75, 8.5, 16, 8.75], "texture": "#0", "rotation": 270},
				"east": {"uv": [10.75, 8.5, 16, 8.75], "texture": "#0", "rotation": 90},
				"south": {"uv": [10.75, 8.5, 16, 8.75], "texture": "#0", "rotation": 90},
				"west": {"uv": [10.75, 8.5, 16, 8.75], "texture": "#0", "rotation": 90},
				"up": {"uv": [15.75, 8.5, 16, 8.75], "texture": "#0", "rotation": 90},
				"down": {"uv": [15.75, 8.5, 16, 8.75], "texture": "#0", "rotation": 90}
			}
		},
		{
			"from": [14, 26.675, 4.25],
			"to": [31, 28.675, 6.25],
			"rotation": {"angle": 22.5, "axis": "z", "origin": [30.5, 27.675, 5.25]},
			"faces": {
				"north": {"uv": [10.75, 8, 16, 8.75], "texture": "#0"},
				"east": {"uv": [10.75, 8, 11.5, 8.75], "texture": "#0"},
				"south": {"uv": [10.75, 8, 16, 8.75], "texture": "#0"},
				"west": {"uv": [15.25, 8, 16, 8.75], "texture": "#0"},
				"up": {"uv": [10.75, 8, 16, 8.75], "texture": "#0"},
				"down": {"uv": [10.75, 8, 16, 8.75], "texture": "#0"}
			}
		},
		{
			"from": [-14.25, 6.775, 5.25],
			"to": [-14.25, 27.775, 26.25],
			"rotation": {"angle": -22.5, "axis": "z", "origin": [-14.25, 27.775, 15.75]},
			"faces": {
				"north": {"uv": [0, 8, 5.25, 13.25], "texture": "#0", "rotation": 90},
				"east": {"uv": [0, 13.25, 5.25, 8], "texture": "#0", "rotation": 90},
				"south": {"uv": [0, 8, 5.25, 13.25], "texture": "#0", "rotation": 270},
				"west": {"uv": [0, 8, 5.25, 13.25], "texture": "#0", "rotation": 90},
				"up": {"uv": [0, 8, 5.25, 13.25], "texture": "#0", "rotation": 270},
				"down": {"uv": [0, 8, 5.25, 13.25], "texture": "#0", "rotation": 270}
			}
		},
		{
			"from": [-14.25, 27.775, 5.25],
			"to": [6.75, 27.775, 26.25],
			"rotation": {"angle": -22.5, "axis": "z", "origin": [-14.25, 27.775, 15.75]},
			"faces": {
				"north": {"uv": [0, 8, 5.25, 13.25], "texture": "#0"},
				"east": {"uv": [0, 8, 5.25, 13.25], "texture": "#0"},
				"south": {"uv": [0, 8, 5.25, 13.25], "texture": "#0"},
				"west": {"uv": [0, 8, 5.25, 13.25], "texture": "#0"},
				"up": {"uv": [5.25, 8, 10.5, 13.25], "texture": "#0", "rotation": 180},
				"down": {"uv": [5.25, 13.25, 10.5, 8], "texture": "#0", "rotation": 180}
			}
		},
		{
			"from": [-14.75, 22.775, 4.75],
			"to": [-13.75, 27.775, 5.75],
			"rotation": {"angle": -22.5, "axis": "z", "origin": [-14.25, 27.775, 5.25]},
			"faces": {
				"north": {"uv": [11, 8.5, 12.75, 8.75], "texture": "#0", "rotation": 90},
				"east": {"uv": [11, 8.5, 12.75, 8.75], "texture": "#0", "rotation": 270},
				"south": {"uv": [11, 8.5, 12.75, 8.75], "texture": "#0", "rotation": 270},
				"west": {"uv": [11, 8.5, 12.75, 8.75], "texture": "#0", "rotation": 270},
				"up": {"uv": [11, 8.5, 12.75, 8.75], "texture": "#0", "rotation": 270},
				"down": {"uv": [11, 8.5, 12.75, 8.75], "texture": "#0", "rotation": 270}
			}
		},
		{
			"from": [-14.25, 26.775, 4.25],
			"to": [-10.25, 28.775, 6.25],
			"rotation": {"angle": -22.5, "axis": "z", "origin": [-14.25, 27.775, 5.25]},
			"faces": {
				"north": {"uv": [14.5, 8, 16, 8.75], "texture": "#0"},
				"east": {"uv": [14.5, 8, 16, 8.75], "texture": "#0"},
				"south": {"uv": [14.5, 8, 16, 8.75], "texture": "#0"},
				"west": {"uv": [15.25, 8, 16, 8.75], "texture": "#0"},
				"up": {"uv": [14.5, 8, 16, 8.75], "texture": "#0"},
				"down": {"uv": [14.5, 8, 16, 8.75], "texture": "#0"}
			}
		},
		{
			"from": [-14.75, 6.775, 4.75],
			"to": [-13.75, 23.775, 5.75],
			"rotation": {"angle": -22.5, "axis": "z", "origin": [-14.25, 27.775, 5.25]},
			"faces": {
				"north": {"uv": [10.75, 8.5, 16, 8.75], "texture": "#0", "rotation": 90},
				"east": {"uv": [10.75, 8.5, 16, 8.75], "texture": "#0", "rotation": 270},
				"south": {"uv": [10.75, 8.5, 16, 8.75], "texture": "#0", "rotation": 270},
				"west": {"uv": [10.75, 8.5, 16, 8.75], "texture": "#0", "rotation": 270},
				"up": {"uv": [15.75, 8.5, 16, 8.75], "texture": "#0", "rotation": 270},
				"down": {"uv": [15.75, 8.5, 16, 8.75], "texture": "#0", "rotation": 270}
			}
		},
		{
			"from": [-10.25, 26.775, 4.25],
			"to": [6.75, 28.775, 6.25],
			"rotation": {"angle": -22.5, "axis": "z", "origin": [-14.25, 27.775, 5.25]},
			"faces": {
				"north": {"uv": [10.75, 8, 16, 8.75], "texture": "#0"},
				"east": {"uv": [10.75, 8, 11.5, 8.75], "texture": "#0"},
				"south": {"uv": [10.75, 8, 16, 8.75], "texture": "#0"},
				"west": {"uv": [15.25, 8, 16, 8.75], "texture": "#0"},
				"up": {"uv": [10.75, 8, 16, 8.75], "texture": "#0"},
				"down": {"uv": [10.75, 8, 16, 8.75], "texture": "#0"}
			}
		},
		{
			"from": [2.5, 2.75, 21],
			"to": [5.5, 5.75, 30],
			"rotation": {"angle": -22.5, "axis": "x", "origin": [4, 4.25, 25.5]},
			"faces": {
				"north": {"uv": [0, 15.25, 0.75, 16], "texture": "#0", "rotation": 180},
				"east": {"uv": [9, 13.25, 9.75, 16], "texture": "#0", "rotation": 270},
				"south": {"uv": [0, 15.25, 0.75, 16], "texture": "#0"},
				"west": {"uv": [9, 13.25, 9.75, 16], "texture": "#0", "rotation": 90},
				"up": {"uv": [9, 13.25, 9.75, 16], "texture": "#0", "rotation": 180},
				"down": {"uv": [9, 13.25, 9.75, 16], "texture": "#0"}
			}
		},
		{
			"from": [2, 6.75, 21],
			"to": [6, 10.75, 30],
			"rotation": {"angle": 22.5, "axis": "x", "origin": [4, 8.75, 25.5]},
			"faces": {
				"north": {"uv": [10.75, 4.75, 11.75, 5.75], "texture": "#0", "rotation": 180},
				"east": {"uv": [7.75, 13.25, 8.75, 16], "texture": "#0", "rotation": 90},
				"south": {"uv": [10.75, 4.75, 11.75, 5.75], "texture": "#0"},
				"west": {"uv": [7.75, 13.25, 8.75, 16], "texture": "#0", "rotation": 270},
				"up": {"uv": [7.75, 13.25, 8.75, 16], "texture": "#0"},
				"down": {"uv": [7.75, 13.25, 8.75, 16], "texture": "#0", "rotation": 180}
			}
		},
		{
			"from": [1, 0, 15.75],
			"to": [7, 2, 24.75],
			"faces": {
				"north": {"uv": [11, 12.5, 12.5, 13], "texture": "#0"},
				"east": {"uv": [13, 12.5, 14.5, 13], "texture": "#0", "rotation": 180},
				"south": {"uv": [13, 12.5, 14.5, 13], "texture": "#0", "rotation": 180},
				"west": {"uv": [13, 12.5, 14.5, 13], "texture": "#0", "rotation": 180},
				"up": {"uv": [11, 10.25, 12.5, 12.5], "texture": "#0", "rotation": 180},
				"down": {"uv": [12.5, 10.25, 11, 12.5], "texture": "#0"}
			}
		},
		{
			"from": [10.5, 2.75, 21],
			"to": [13.5, 5.75, 30],
			"rotation": {"angle": -22.5, "axis": "x", "origin": [12, 4.25, 25.5]},
			"faces": {
				"north": {"uv": [0, 15.25, 0.75, 16], "texture": "#0", "rotation": 180},
				"east": {"uv": [9, 13.25, 9.75, 16], "texture": "#0", "rotation": 270},
				"south": {"uv": [0, 15.25, 0.75, 16], "texture": "#0"},
				"west": {"uv": [9, 13.25, 9.75, 16], "texture": "#0", "rotation": 90},
				"up": {"uv": [9, 13.25, 9.75, 16], "texture": "#0", "rotation": 180},
				"down": {"uv": [9, 13.25, 9.75, 16], "texture": "#0"}
			}
		},
		{
			"from": [10, 6.75, 21],
			"to": [14, 10.75, 30],
			"rotation": {"angle": 22.5, "axis": "x", "origin": [12, 8.75, 25.5]},
			"faces": {
				"north": {"uv": [10.75, 4.75, 11.75, 5.75], "texture": "#0", "rotation": 180},
				"east": {"uv": [7.75, 13.25, 8.75, 16], "texture": "#0", "rotation": 90},
				"south": {"uv": [10.75, 4.75, 11.75, 5.75], "texture": "#0"},
				"west": {"uv": [7.75, 13.25, 8.75, 16], "texture": "#0", "rotation": 270},
				"up": {"uv": [7.75, 13.25, 8.75, 16], "texture": "#0"},
				"down": {"uv": [7.75, 13.25, 8.75, 16], "texture": "#0", "rotation": 180}
			}
		},
		{
			"from": [9, 0, 15.75],
			"to": [15, 2, 24.75],
			"faces": {
				"north": {"uv": [11, 12.5, 12.5, 13], "texture": "#0"},
				"east": {"uv": [13, 12.5, 14.5, 13], "texture": "#0", "rotation": 180},
				"south": {"uv": [13, 12.5, 14.5, 13], "texture": "#0", "rotation": 180},
				"west": {"uv": [13, 12.5, 14.5, 13], "texture": "#0", "rotation": 180},
				"up": {"uv": [11, 10.25, 12.5, 12.5], "texture": "#0", "rotation": 180},
				"down": {"uv": [12.5, 10.25, 11, 12.5], "texture": "#0"}
			}
		},
		{
			"from": [10.5, 1, 8],
			"to": [12.5, 7, 10],
			"faces": {
				"north": {"uv": [1.25, 13.5, 1.75, 15], "texture": "#0"},
				"east": {"uv": [1.25, 13.5, 1.75, 15], "texture": "#0"},
				"south": {"uv": [1.25, 13.5, 1.75, 15], "texture": "#0"},
				"west": {"uv": [1.25, 13.5, 1.75, 15], "texture": "#0"},
				"up": {"uv": [1.25, 13.5, 1.75, 15], "texture": "#0"},
				"down": {"uv": [1.25, 13.5, 1.75, 15], "texture": "#0"}
			}
		},
		{
			"from": [10, 7, 7.5],
			"to": [13, 13, 10.5],
			"faces": {
				"north": {"uv": [0, 13.5, 0.75, 15], "texture": "#0"},
				"east": {"uv": [0, 13.5, 0.75, 15], "texture": "#0"},
				"south": {"uv": [0, 13.5, 0.75, 15], "texture": "#0"},
				"west": {"uv": [0, 13.5, 0.75, 15], "texture": "#0"},
				"up": {"uv": [0, 15.25, 0.75, 16], "texture": "#0"},
				"down": {"uv": [0, 15.25, 0.75, 16], "texture": "#0"}
			}
		},
		{
			"from": [10, 0, 4.5],
			"to": [13, 1, 10.5],
			"faces": {
				"north": {"uv": [3, 15.5, 3.75, 15.75], "texture": "#0"},
				"east": {"uv": [4.5, 15.5, 6, 15.75], "texture": "#0"},
				"south": {"uv": [4.5, 15.5, 6, 15.75], "texture": "#0"},
				"west": {"uv": [4.5, 15.5, 6, 15.75], "texture": "#0"},
				"up": {"uv": [3, 14, 3.75, 15.5], "texture": "#0", "rotation": 180},
				"down": {"uv": [3.75, 14, 4.5, 15.5], "texture": "#0"}
			}
		},
		{
			"from": [2.5, 1, 8],
			"to": [4.5, 7, 10],
			"faces": {
				"north": {"uv": [1.25, 13.5, 1.75, 15], "texture": "#0"},
				"east": {"uv": [1.25, 13.5, 1.75, 15], "texture": "#0"},
				"south": {"uv": [1.25, 13.5, 1.75, 15], "texture": "#0"},
				"west": {"uv": [1.25, 13.5, 1.75, 15], "texture": "#0"},
				"up": {"uv": [1.25, 13.5, 1.75, 15], "texture": "#0"},
				"down": {"uv": [1.25, 13.5, 1.75, 15], "texture": "#0"}
			}
		},
		{
			"from": [2, 7, 7.5],
			"to": [5, 13, 10.5],
			"faces": {
				"north": {"uv": [0, 13.5, 0.75, 15], "texture": "#0"},
				"east": {"uv": [0, 13.5, 0.75, 15], "texture": "#0"},
				"south": {"uv": [0, 13.5, 0.75, 15], "texture": "#0"},
				"west": {"uv": [0, 13.5, 0.75, 15], "texture": "#0"},
				"up": {"uv": [0, 15.25, 0.75, 16], "texture": "#0"},
				"down": {"uv": [0, 15.25, 0.75, 16], "texture": "#0"}
			}
		},
		{
			"from": [2, 0, 4.5],
			"to": [5, 1, 10.5],
			"faces": {
				"north": {"uv": [3, 15.5, 3.75, 15.75], "texture": "#0"},
				"east": {"uv": [4.5, 15.5, 6, 15.75], "texture": "#0"},
				"south": {"uv": [4.5, 15.5, 6, 15.75], "texture": "#0"},
				"west": {"uv": [4.5, 15.5, 6, 15.75], "texture": "#0"},
				"up": {"uv": [3, 14, 3.75, 15.5], "texture": "#0", "rotation": 180},
				"down": {"uv": [3.75, 14, 4.5, 15.5], "texture": "#0"}
			}
		},
		{
			"from": [6, 20, 1.325],
			"to": [10, 24, 5.325],
			"rotation": {"angle": -22.5, "axis": "x", "origin": [8, 22, 3.325]},
			"faces": {
				"north": {"uv": [10.75, 4.75, 11.75, 5.75], "texture": "#0", "rotation": 180},
				"east": {"uv": [10.75, 4.75, 11.75, 5.75], "texture": "#0", "rotation": 270},
				"south": {"uv": [10.75, 4.75, 11.75, 5.75], "texture": "#0"},
				"west": {"uv": [10.75, 4.75, 11.75, 5.75], "texture": "#0", "rotation": 90},
				"up": {"uv": [10.75, 4.75, 11.75, 5.75], "texture": "#0", "rotation": 180},
				"down": {"uv": [10.75, 4.75, 11.75, 5.75], "texture": "#0"}
			}
		},
		{
			"from": [7.75, 21, 5.325],
			"to": [8.25, 23.25, 6.575],
			"rotation": {"angle": -22.5, "axis": "x", "origin": [8, 22, 3.325]},
			"faces": {
				"north": {"uv": [11, 2, 11.25, 2.75], "texture": "#0", "rotation": 180},
				"east": {"uv": [10, 2.75, 10.75, 3.25], "texture": "#0", "rotation": 270},
				"south": {"uv": [10.75, 2, 11, 2.75], "texture": "#0"},
				"west": {"uv": [11.25, 2.75, 12, 3.25], "texture": "#0", "rotation": 90},
				"up": {"uv": [10.75, 2.75, 11, 3.25], "texture": "#0", "rotation": 180},
				"down": {"uv": [11, 2.75, 11.25, 3.25], "texture": "#0"}
			}
		},
		{
			"from": [6, 16.75, 1.825],
			"to": [10, 20.75, 5.825],
			"rotation": {"angle": 0, "axis": "x", "origin": [8, 18.75, 3.825]},
			"faces": {
				"north": {"uv": [10.75, 4.75, 11.75, 5.75], "texture": "#0", "rotation": 180},
				"east": {"uv": [10.75, 4.75, 11.75, 5.75], "texture": "#0", "rotation": 270},
				"south": {"uv": [10.75, 4.75, 11.75, 5.75], "texture": "#0"},
				"west": {"uv": [10.75, 4.75, 11.75, 5.75], "texture": "#0", "rotation": 90},
				"up": {"uv": [10.75, 4.75, 11.75, 5.75], "texture": "#0", "rotation": 180},
				"down": {"uv": [10.75, 4.75, 11.75, 5.75], "texture": "#0"}
			}
		},
		{
			"from": [6, 23, -0.675],
			"to": [10, 27, 3.325],
			"rotation": {"angle": 45, "axis": "x", "origin": [8, 25, 1.325]},
			"faces": {
				"north": {"uv": [10.75, 4.75, 11.75, 5.75], "texture": "#0"},
				"east": {"uv": [10.75, 4.75, 11.75, 5.75], "texture": "#0"},
				"south": {"uv": [10.75, 4.75, 11.75, 5.75], "texture": "#0"},
				"west": {"uv": [10.75, 4.75, 11.75, 5.75], "texture": "#0"},
				"up": {"uv": [10.75, 4.75, 11.75, 5.75], "texture": "#0"},
				"down": {"uv": [10.75, 4.75, 11.75, 5.75], "texture": "#0"}
			}
		},
		{
			"from": [7.75, 27, 0.075],
			"to": [8.25, 28.25, 2.325],
			"rotation": {"angle": 45, "axis": "x", "origin": [8, 25, 1.325]},
			"faces": {
				"north": {"uv": [10.75, 2.75, 11, 3.25], "texture": "#0"},
				"east": {"uv": [10, 2.75, 10.75, 3.25], "texture": "#0"},
				"south": {"uv": [11, 2.75, 11.25, 3.25], "texture": "#0"},
				"west": {"uv": [11.25, 2.75, 12, 3.25], "texture": "#0"},
				"up": {"uv": [10.75, 2, 11, 2.75], "texture": "#0"},
				"down": {"uv": [11, 2, 11.25, 2.75], "texture": "#0"}
			}
		},
		{
			"from": [6, 25, -3.175],
			"to": [10, 29, 0.825],
			"rotation": {"angle": 22.5, "axis": "x", "origin": [8, 27, -1.175]},
			"faces": {
				"north": {"uv": [10.75, 4.75, 11.75, 5.75], "texture": "#0"},
				"east": {"uv": [10.75, 4.75, 11.75, 5.75], "texture": "#0"},
				"south": {"uv": [10.75, 4.75, 11.75, 5.75], "texture": "#0"},
				"west": {"uv": [10.75, 4.75, 11.75, 5.75], "texture": "#0"},
				"up": {"uv": [10.75, 4.75, 11.75, 5.75], "texture": "#0"},
				"down": {"uv": [10.75, 4.75, 11.75, 5.75], "texture": "#0"}
			}
		},
		{
			"from": [7.75, 29, -2.425],
			"to": [8.25, 30.25, -0.175],
			"rotation": {"angle": 22.5, "axis": "x", "origin": [8, 27, -1.175]},
			"faces": {
				"north": {"uv": [10.75, 2.75, 11, 3.25], "texture": "#0"},
				"east": {"uv": [10, 2.75, 10.75, 3.25], "texture": "#0"},
				"south": {"uv": [11, 2.75, 11.25, 3.25], "texture": "#0"},
				"west": {"uv": [11.25, 2.75, 12, 3.25], "texture": "#0"},
				"up": {"uv": [10.75, 2, 11, 2.75], "texture": "#0"},
				"down": {"uv": [11, 2, 11.25, 2.75], "texture": "#0"}
			}
		},
		{
			"from": [6, 25.5, -6.675],
			"to": [10, 29.5, -2.675],
			"rotation": {"angle": 0, "axis": "x", "origin": [8, 27.5, -4.675]},
			"faces": {
				"north": {"uv": [10.75, 4.75, 11.75, 5.75], "texture": "#0"},
				"east": {"uv": [10.75, 4.75, 11.75, 5.75], "texture": "#0"},
				"south": {"uv": [10.75, 4.75, 11.75, 5.75], "texture": "#0"},
				"west": {"uv": [10.75, 4.75, 11.75, 5.75], "texture": "#0"},
				"up": {"uv": [10.75, 4.75, 11.75, 5.75], "texture": "#0"},
				"down": {"uv": [10.75, 4.75, 11.75, 5.75], "texture": "#0"}
			}
		},
		{
			"from": [7.75, 29.5, -5.925],
			"to": [8.25, 30.75, -3.675],
			"rotation": {"angle": 0, "axis": "x", "origin": [8, 27.5, -4.675]},
			"faces": {
				"north": {"uv": [10.75, 2.75, 11, 3.25], "texture": "#0"},
				"east": {"uv": [10, 2.75, 10.75, 3.25], "texture": "#0"},
				"south": {"uv": [11, 2.75, 11.25, 3.25], "texture": "#0"},
				"west": {"uv": [11.25, 2.75, 12, 3.25], "texture": "#0"},
				"up": {"uv": [10.75, 2, 11, 2.75], "texture": "#0"},
				"down": {"uv": [11, 2, 11.25, 2.75], "texture": "#0"}
			}
		},
		{
			"from": [6, 7.875, 24.45],
			"to": [10, 11.875, 28.45],
			"rotation": {"angle": -22.5, "axis": "x", "origin": [8, 9.875, 26.45]},
			"faces": {
				"north": {"uv": [10.75, 4.75, 11.75, 5.75], "texture": "#0", "rotation": 180},
				"east": {"uv": [10.75, 4.75, 11.75, 5.75], "texture": "#0", "rotation": 270},
				"south": {"uv": [10.75, 4.75, 11.75, 5.75], "texture": "#0"},
				"west": {"uv": [10.75, 4.75, 11.75, 5.75], "texture": "#0", "rotation": 90},
				"up": {"uv": [10.75, 4.75, 11.75, 5.75], "texture": "#0", "rotation": 180},
				"down": {"uv": [10.75, 4.75, 11.75, 5.75], "texture": "#0"}
			}
		},
		{
			"from": [7.75, 8.875, 28.45],
			"to": [8.25, 11.125, 29.7],
			"rotation": {"angle": -22.5, "axis": "x", "origin": [8, 10, 26.45]},
			"faces": {
				"north": {"uv": [11, 2, 11.25, 2.75], "texture": "#0", "rotation": 180},
				"east": {"uv": [10, 2.75, 10.75, 3.25], "texture": "#0", "rotation": 270},
				"south": {"uv": [10.75, 2, 11, 2.75], "texture": "#0"},
				"west": {"uv": [11.25, 2.75, 12, 3.25], "texture": "#0", "rotation": 90},
				"up": {"uv": [10.75, 2.75, 11, 3.25], "texture": "#0", "rotation": 180},
				"down": {"uv": [11, 2.75, 11.25, 3.25], "texture": "#0"}
			}
		},
		{
			"from": [1.75, 0.75, 25.025],
			"to": [5.75, 4.75, 29.025],
			"rotation": {"angle": 0, "axis": "z", "origin": [3.75, 2.75, 27.025]},
			"faces": {
				"north": {"uv": [10.75, 4.75, 11.75, 5.75], "texture": "#0"},
				"east": {"uv": [10.75, 4.75, 11.75, 5.75], "texture": "#0"},
				"south": {"uv": [10.75, 4.75, 11.75, 5.75], "texture": "#0"},
				"west": {"uv": [10.75, 4.75, 11.75, 5.75], "texture": "#0"},
				"up": {"uv": [10.75, 4.75, 11.75, 5.75], "texture": "#0"},
				"down": {"uv": [10.75, 4.75, 11.75, 5.75], "texture": "#0"}
			}
		},
		{
			"from": [2.5, 2.5, 28.95],
			"to": [4.75, 3, 30.2],
			"rotation": {"angle": 0, "axis": "z", "origin": [3.625, 2.75, 29.575]},
			"faces": {
				"north": {"uv": [10, 2.75, 10.75, 3.25], "texture": "#0", "rotation": 180},
				"east": {"uv": [10, 2.75, 10.75, 3.25], "texture": "#0", "rotation": 180},
				"south": {"uv": [10, 2.75, 10.75, 3.25], "texture": "#0", "rotation": 180},
				"west": {"uv": [10, 2.75, 10.75, 3.25], "texture": "#0", "rotation": 180},
				"up": {"uv": [10.75, 2.75, 10, 3.25], "texture": "#0", "rotation": 180},
				"down": {"uv": [10, 2.75, 10.75, 3.25], "texture": "#0"}
			}
		},
		{
			"from": [-4.5, 0, 9.575],
			"to": [-0.5, 4, 13.575],
			"rotation": {"angle": 0, "axis": "y", "origin": [-2.5, 2, 11.575]},
			"faces": {
				"north": {"uv": [10.75, 4.75, 11.75, 5.75], "texture": "#0"},
				"east": {"uv": [10.75, 4.75, 11.75, 5.75], "texture": "#0"},
				"south": {"uv": [10.75, 4.75, 11.75, 5.75], "texture": "#0"},
				"west": {"uv": [10.75, 4.75, 11.75, 5.75], "texture": "#0"},
				"up": {"uv": [10.75, 4.75, 11.75, 5.75], "texture": "#0"},
				"down": {"uv": [10.75, 4.75, 11.75, 5.75], "texture": "#0"}
			}
		},
		{
			"from": [-2.75, 4, 10.325],
			"to": [-2.25, 5.25, 12.575],
			"rotation": {"angle": 0, "axis": "y", "origin": [-2.5, 4.625, 11.45]},
			"faces": {
				"north": {"uv": [10.75, 2.75, 11, 3.25], "texture": "#0"},
				"east": {"uv": [10, 2.75, 10.75, 3.25], "texture": "#0"},
				"south": {"uv": [11, 2.75, 11.25, 3.25], "texture": "#0"},
				"west": {"uv": [11.25, 2.75, 12, 3.25], "texture": "#0"},
				"up": {"uv": [10.75, 2, 11, 2.75], "texture": "#0"},
				"down": {"uv": [11, 2, 11.25, 2.75], "texture": "#0"}
			}
		},
		{
			"from": [-4.5, 0, 17.575],
			"to": [-0.5, 4, 21.575],
			"rotation": {"angle": 0, "axis": "y", "origin": [-2.5, 2, 19.575]},
			"faces": {
				"north": {"uv": [10.75, 4.75, 11.75, 5.75], "texture": "#0"},
				"east": {"uv": [10.75, 4.75, 11.75, 5.75], "texture": "#0"},
				"south": {"uv": [10.75, 4.75, 11.75, 5.75], "texture": "#0"},
				"west": {"uv": [10.75, 4.75, 11.75, 5.75], "texture": "#0"},
				"up": {"uv": [10.75, 4.75, 11.75, 5.75], "texture": "#0"},
				"down": {"uv": [10.75, 4.75, 11.75, 5.75], "texture": "#0"}
			}
		},
		{
			"from": [-2.75, 4, 18.325],
			"to": [-2.25, 5.25, 20.575],
			"rotation": {"angle": 0, "axis": "y", "origin": [-2.5, 4.625, 19.45]},
			"faces": {
				"north": {"uv": [10.75, 2.75, 11, 3.25], "texture": "#0"},
				"east": {"uv": [10, 2.75, 10.75, 3.25], "texture": "#0"},
				"south": {"uv": [11, 2.75, 11.25, 3.25], "texture": "#0"},
				"west": {"uv": [11.25, 2.75, 12, 3.25], "texture": "#0"},
				"up": {"uv": [10.75, 2, 11, 2.75], "texture": "#0"},
				"down": {"uv": [11, 2, 11.25, 2.75], "texture": "#0"}
			}
		}
	],
	"display": {
		"thirdperson_righthand": {
			"scale": [0.35, 0.35, 0.35],
			"translation": [0.5, 2.5, -3]
		},
		"firstperson_righthand": {
			"translation": [13.5, -11.5, -7],
			"rotation": [0, 124, 0]
		},
		"firstperson_lefthand": {
			"rotation": [0, 124, 0],
			"translation": [13.5, -11.5, -7]
		},
		"head": {
			"translation": [0, 14, -6]
		},
		"ground": {
			"scale": [0.5, 0.5, 0.5],
			"translation": [0, 0, 0]
		},
		"fixed": {
			"scale": [0.6, 0.6, 0.6],
			"translation": [0, -5.5, -1.5]
		},
		"gui": {
			"scale": [0.4, 0.4, 0.4],
			"rotation": [30, 225, 0],
			"translation": [3, -4, 0.5]
		},
		"thirdperson_lefthand": {
			"scale": [0.35, 0.35, 0.35],
			"translation": [0.5, 2.5, -3]
		}
	},
	"groups": [
		{
			"name": "Head",
			"isOpen": false,
			"shade": true,
			"display": {
				"visibility": true,
				"autouv": true
			},
			"children": [0, 1, 2, 3, 4, 5, 6]
		},
		{
			"name": "Body",
			"isOpen": false,
			"shade": true,
			"display": {
				"visibility": true,
				"autouv": true
			},
			"children": [7, 8, 9, 10]
		},
		{
			"name": "Tail.1",
			"isOpen": true,
			"shade": true,
			"display": {
				"visibility": true,
				"autouv": true
			},
			"children": []
		},
		{
			"name": "Tail.2",
			"isOpen": true,
			"shade": true,
			"display": {
				"visibility": true,
				"autouv": true
			},
			"children": []
		},
		{
			"name": "Tail.3",
			"isOpen": true,
			"shade": true,
			"display": {
				"visibility": true,
				"autouv": true
			},
			"children": [11, 12]
		},
		{
			"name": "Tail.4",
			"isOpen": true,
			"shade": true,
			"display": {
				"visibility": true,
				"autouv": true
			},
			"children": [13, 14]
		},
		{
			"name": "Tail.5",
			"isOpen": true,
			"shade": true,
			"display": {
				"visibility": true,
				"autouv": true
			},
			"children": [15, 16]
		},
		{
			"name": "Tail.6",
			"isOpen": true,
			"shade": true,
			"display": {
				"visibility": true,
				"autouv": true
			},
			"children": [17, 18]
		},
		{
			"name": "Tail.7",
			"isOpen": true,
			"shade": true,
			"display": {
				"visibility": true,
				"autouv": true
			},
			"children": [19, 20]
		},
		{
			"name": "Tail.8",
			"isOpen": true,
			"shade": true,
			"display": {
				"visibility": true,
				"autouv": true
			},
			"children": [21, 22]
		},
		{
			"name": "Tail.9",
			"isOpen": true,
			"shade": true,
			"display": {
				"visibility": true,
				"autouv": true
			},
			"children": []
		},
		{
			"name": "Tail.10",
			"isOpen": false,
			"shade": true,
			"display": {
				"visibility": true,
				"autouv": true
			},
			"children": [23, 24]
		},
		{
			"name": "Wing.R",
			"isOpen": false,
			"shade": true,
			"display": {
				"visibility": true,
				"autouv": true
			},
			"children": [25, 26, 27, 28, 29, 30]
		},
		{
			"name": "Wing.L",
			"isOpen": true,
			"shade": true,
			"display": {
				"visibility": true,
				"autouv": true
			},
			"children": [31, 32, 33, 34, 35, 36]
		},
		{
			"name": "RearLeg.L",
			"isOpen": false,
			"shade": true,
			"display": {
				"visibility": true,
				"autouv": true
			},
			"children": [37, 38, 39]
		},
		{
			"name": "RearLeg.R",
			"isOpen": false,
			"shade": true,
			"display": {
				"visibility": true,
				"autouv": true
			},
			"children": [40, 41, 42]
		},
		{
			"name": "FrontLeg.L",
			"isOpen": false,
			"shade": true,
			"display": {
				"visibility": true,
				"autouv": true
			},
			"children": [43, 44, 45]
		},
		{
			"name": "FrontLeg.L",
			"isOpen": false,
			"shade": true,
			"display": {
				"visibility": true,
				"autouv": true
			},
			"children": [46, 47, 48]
		},
		{
			"name": "Neck.4",
			"isOpen": false,
			"shade": true,
			"display": {
				"visibility": true,
				"autouv": true
			},
			"children": [49, 50]
		},
		{
			"name": "Neck.5",
			"isOpen": false,
			"shade": true,
			"display": {
				"visibility": true,
				"autouv": true
			},
			"children": [51]
		},
		{
			"name": "Neck.3",
			"isOpen": false,
			"shade": true,
			"display": {
				"visibility": true,
				"autouv": true
			},
			"children": [52, 53]
		},
		{
			"name": "Neck.2",
			"shade": true,
			"display": {
				"visibility": true,
				"autouv": true
			},
			"children": [54, 55]
		},
		{
			"name": "Neck.1",
			"shade": true,
			"display": {
				"visibility": true,
				"autouv": true
			},
			"children": [56, 57]
		},
		{
			"name": "Tail.11",
			"isOpen": false,
			"shade": true,
			"display": {
				"visibility": true,
				"autouv": true
			},
			"children": [58, 59]
		},
		{
			"name": "Tail.7",
			"shade": true,
			"display": {
				"visibility": true,
				"autouv": true
			},
			"children": [60, 61]
		},
		{
			"name": "Tail.5",
			"isOpen": true,
			"shade": true,
			"display": {
				"visibility": true,
				"autouv": true
			},
			"children": [62, 63]
		},
		{
			"name": "Tail.5",
			"shade": true,
			"display": {
				"visibility": true,
				"autouv": true
			},
			"children": [64, 65]
		}
	]
}